[{"word": "开发", "value": 4}, {"word": "Java", "value": 4}, {"word": "实施", "value": 3}, {"word": "涉及", "value": 3}, {"word": "物", "value": 3}, {"word": "智能", "value": 3}, {"word": "硬件", "value": 3}, {"word": "数据", "value": 3}, {"word": "项目", "value": 2}, {"word": "施工", "value": 2}, {"word": "渠道", "value": 2}, {"word": "销售", "value": 2}, {"word": "网站", "value": 2}, {"word": "中高", "value": 2}, {"word": "中高级", "value": 2}, {"word": "研发", "value": 2}, {"word": "前端", "value": 2}, {"word": "运维", "value": 2}, {"word": "数据库", "value": 2}, {"word": "据库", "value": 2}, {"word": "售前", "value": 2}, {"word": "支持", "value": 2}, {"word": "产品", "value": 2}, {"word": "Android", "value": 2}, {"word": "平面设计", "value": 1}, {"word": "UI", "value": 1}, {"word": "美工", "value": 1}, {"word": "文案", "value": 1}, {"word": "策划", "value": 1}, {"word": "编辑", "value": 1}, {"word": "网络", "value": 1}, {"word": "推广", "value": 1}, {"word": "PHP", "value": 1}, {"word": "Web", "value": 1}, {"word": "前端开发", "value": 1}, {"word": "HTML5CSS3", "value": 1}, {"word": "web", "value": 1}, {"word": "C++", "value": 1}, {"word": "架构", "value": 1}, {"word": "架构师", "value": 1}, {"word": "HCMPeoplesoftCRMSiebel", "value": 1}, {"word": "或", "value": 1}, {"word": "技术", "value": 1}, {"word": "技术支持", "value": 1}, {"word": "韩语", "value": 1}, {"word": "DBA", "value": 1}, {"word": "法律", "value": 1}, {"word": "法律顾问", "value": 1}, {"word": "法务", "value": 1}, {"word": "沈阳", "value": 1}, {"word": "网页", "value": 1}, {"word": "产品设计", "value": 1}, {"word": "GIS", "value": 1}]