[{"Provience":"\u8fbd\u5b81","City":"\u6c88\u9633\u5e02","CompanyShortName":"\u676d\u5dde\u5929\u4e3d\u79d1\u6280\u6709\u9650\u516c\u53f8","IndustryField":"\u79fb\u52a8\u4e92\u8054\u7f51 \u00b7 \u786c\u4ef6","Upper class of industry":"IT\u6280\u672f,\u7535\u5b50\u5236\u9020"},{"Provience":"\u8fbd\u5b81","City":"\u6c88\u9633\u5e02","CompanyShortName":"\u5317\u4eac\u82f9\u679c\u77e5\u79d1\u6280\u6709\u9650\u516c\u53f8","IndustryField":"\u79fb\u52a8\u4e92\u8054\u7f51 \u00b7 \u786c\u4ef6","Upper class of industry":"IT\u6280\u672f,\u7535\u5b50\u5236\u9020"},{"Provience":"\u8fbd\u5b81","City":"\u6c88\u9633\u5e02","CompanyShortName":"\u798f\u5efa\u8054\u8fea\u5546\u7528\u8bbe\u5907\u6709\u9650\u516c\u53f8","IndustryField":"\u79fb\u52a8\u4e92\u8054\u7f51 \u00b7 \u786c\u4ef6","Upper class of industry":"IT\u6280\u672f,\u7535\u5b50\u5236\u9020"},{"Provience":"\u8fbd\u5b81","City":"\u6c88\u9633\u5e02","CompanyShortName":"\u6c88\u9633\u9e3f\u5b87\u79d1\u6280\u6709\u9650\u516c\u53f8","IndustryField":"O2O \u00b7 \u786c\u4ef6","Upper class of industry":"IT\u6280\u672f,\u7535\u5b50\u5236\u9020"},{"Provience":"\u8fbd\u5b81","City":"\u6c88\u9633\u5e02","CompanyShortName":"\u6c88\u9633\u667a\u6d4b\u79d1\u6280\u6709\u9650\u516c\u53f8","IndustryField":"\u786c\u4ef6 \u00b7 \u79fb\u52a8\u4e92\u8054\u7f51","Upper class of industry":"IT\u6280\u672f,\u7535\u5b50\u5236\u9020"},{"Provience":"\u8fbd\u5b81","City":"\u6c88\u9633\u5e02","CompanyShortName":"\u6c88\u9633\u6d77\u98ce\u7f51\u7edc\u79d1\u6280\u6709\u9650\u516c\u53f8","IndustryField":"\u4f01\u4e1a\u670d\u52a1 \u00b7 \u786c\u4ef6","Upper class of industry":"IT\u6280\u672f,\u7535\u5b50\u5236\u9020"}]