[{"Provience":"\u6c5f\u82cf","City":"\u82cf\u5dde\u5e02","CompanyShortName":"\u660a\u7fd4\u7535\u80fd\u8fd0\u52a8\u79d1\u6280\uff08\u6606\u5c71\uff09\u6709\u9650\u516c\u53f8","IndustryField":"\u786c\u4ef6 \u00b7 \u79fb\u52a8\u4e92\u8054\u7f51","Upper class of industry":"IT\u6280\u672f,\u7535\u5b50\u5236\u9020"},{"Provience":"\u6c5f\u82cf","City":"\u82cf\u5dde\u5e02","CompanyShortName":"\u4e0a\u6d77\u797a\u9cb2\u4fe1\u606f\u79d1\u6280\u6709\u9650\u516c\u53f8\u5317\u4eac\u5206\u516c\u53f8","IndustryField":"\u79fb\u52a8\u4e92\u8054\u7f51 \u00b7 \u786c\u4ef6","Upper class of industry":"IT\u6280\u672f,\u7535\u5b50\u5236\u9020"},{"Provience":"\u6c5f\u82cf","City":"\u82cf\u5dde\u5e02","CompanyShortName":"\u82cf\u5dde\u5bcc\u5174\u7eb3\u7535\u5b50\u79d1\u6280\u6709\u9650\u516c\u53f8","IndustryField":"\u4f01\u4e1a\u670d\u52a1 \u00b7 \u786c\u4ef6","Upper class of industry":"IT\u6280\u672f,\u7535\u5b50\u5236\u9020"},{"Provience":"\u6c5f\u82cf","City":"\u82cf\u5dde\u5e02","CompanyShortName":"\u82cf\u5dde\u5de5\u4e1a\u56ed\u533a\u65b0\u5b8f\u535a\u901a\u8baf\u79d1\u6280\u6709\u9650\u516c\u53f8","IndustryField":"\u6570\u636e\u670d\u52a1 \u00b7 \u786c\u4ef6","Upper class of industry":"IT\u6280\u672f,\u7535\u5b50\u5236\u9020"},{"Provience":"\u6c5f\u82cf","City":"\u82cf\u5dde\u5e02","CompanyShortName":"\u4e0a\u6d77\u5fae\u521b\u8f6f\u4ef6\u80a1\u4efd\u6709\u9650\u516c\u53f8\u6df1\u5733\u5206\u516c\u53f8","IndustryField":"\u79fb\u52a8\u4e92\u8054\u7f51 \u00b7 \u786c\u4ef6","Upper class of industry":"IT\u6280\u672f,\u7535\u5b50\u5236\u9020"},{"Provience":"\u6c5f\u82cf","City":"\u82cf\u5dde\u5e02","CompanyShortName":"\u82cf\u5dde\u827e\u679c\u667a\u80fd\u79d1\u6280\u6709\u9650\u516c\u53f8","IndustryField":"\u79fb\u52a8\u4e92\u8054\u7f51 \u00b7 \u786c\u4ef6","Upper class of industry":"IT\u6280\u672f,\u7535\u5b50\u5236\u9020"},{"Provience":"\u6c5f\u82cf","City":"\u82cf\u5dde\u5e02","CompanyShortName":"\u91cd\u5e86\u5496\u5566\u9b54\u54c6\u79d1\u6280\u6709\u9650\u516c\u53f8","IndustryField":"O2O \u00b7 \u786c\u4ef6","Upper class of industry":"IT\u6280\u672f,\u7535\u5b50\u5236\u9020"},{"Provience":"\u6c5f\u82cf","City":"\u82cf\u5dde\u5e02","CompanyShortName":"\u65e0\u9521\u9a8f\u807f\u79d1\u6280\u6709\u9650\u516c\u53f8","IndustryField":"\u79fb\u52a8\u4e92\u8054\u7f51 \u00b7 \u786c\u4ef6","Upper class of industry":"IT\u6280\u672f,\u7535\u5b50\u5236\u9020"},{"Provience":"\u6c5f\u82cf","City":"\u82cf\u5dde\u5e02","CompanyShortName":"\u82cf\u5dde\u56db\u7ef4\u7a7a\u95f4\u667a\u80fd\u79d1\u6280\u6709\u9650\u516c\u53f8","IndustryField":"\u7535\u5b50\u5546\u52a1 \u00b7 \u786c\u4ef6","Upper class of industry":"IT\u6280\u672f,\u7535\u5b50\u5236\u9020"},{"Provience":"\u6c5f\u82cf","City":"\u82cf\u5dde\u5e02","CompanyShortName":"\u82cf\u5dde\u7231\u5427\u7f51\u7edc\u79d1\u6280\u6709\u9650\u516c\u53f8","IndustryField":"\u786c\u4ef6 \u00b7 \u6570\u636e\u670d\u52a1","Upper class of industry":"IT\u6280\u672f,\u7535\u5b50\u5236\u9020"},{"Provience":"\u6c5f\u82cf","City":"\u82cf\u5dde\u5e02","CompanyShortName":"\u7532\u9aa8\u6587","IndustryField":"\u786c\u4ef6 \u00b7 \u6570\u636e\u670d\u52a1","Upper class of industry":"IT\u6280\u672f,\u7535\u5b50\u5236\u9020"},{"Provience":"\u6c5f\u82cf","City":"\u82cf\u5dde\u5e02","CompanyShortName":"\u82cf\u5dde\u5609\u7984\u8baf\u6c47\u667a\u80fd\u79d1\u6280\u6709\u9650\u516c\u53f8","IndustryField":"\u4f01\u4e1a\u670d\u52a1 \u00b7 \u786c\u4ef6","Upper class of industry":"IT\u6280\u672f,\u7535\u5b50\u5236\u9020"},{"Provience":"\u6c5f\u82cf","City":"\u82cf\u5dde\u5e02","CompanyShortName":"\u82cf\u5dde\u4f18\u52bf\u8baf\u901a\u4e92\u8054\u7f51\u79d1\u6280\u6709\u9650\u516c\u53f8","IndustryField":"\u79fb\u52a8\u4e92\u8054\u7f51 \u00b7 \u786c\u4ef6","Upper class of industry":"IT\u6280\u672f,\u7535\u5b50\u5236\u9020"},{"Provience":"\u6c5f\u82cf","City":"\u82cf\u5dde\u5e02","CompanyShortName":"\u82cf\u5dde\u667a\u5947\u80dc\u8f6f\u4ef6\u79d1\u6280\u6709\u9650\u516c\u53f8","IndustryField":"\u79fb\u52a8\u4e92\u8054\u7f51 \u00b7 \u786c\u4ef6","Upper class of industry":"IT\u6280\u672f,\u7535\u5b50\u5236\u9020"},{"Provience":"\u6c5f\u82cf","City":"\u82cf\u5dde\u5e02","CompanyShortName":"\u82cf\u5dde\u5149\u56fe\u667a\u80fd\u79d1\u6280\u6709\u9650\u516c\u53f8","IndustryField":"\u4f01\u4e1a\u670d\u52a1 \u00b7 \u786c\u4ef6","Upper class of industry":"IT\u6280\u672f,\u7535\u5b50\u5236\u9020"},{"Provience":"\u6c5f\u82cf","City":"\u82cf\u5dde\u5e02","CompanyShortName":"\u82cf\u5dde\u4f17\u5929\u529b\u4fe1\u606f\u79d1\u6280\u6709\u9650\u516c\u53f8","IndustryField":"\u79fb\u52a8\u4e92\u8054\u7f51 \u00b7 \u786c\u4ef6","Upper class of industry":"IT\u6280\u672f,\u7535\u5b50\u5236\u9020"},{"Provience":"\u6c5f\u82cf","City":"\u82cf\u5dde\u5e02","CompanyShortName":"\u82cf\u5dde\u5947\u68a6\u8005\u7f51\u7edc\u79d1\u6280\u6709\u9650\u516c\u53f8","IndustryField":"\u79fb\u52a8\u4e92\u8054\u7f51 \u00b7 \u786c\u4ef6","Upper class of industry":"IT\u6280\u672f,\u7535\u5b50\u5236\u9020"},{"Provience":"\u6c5f\u82cf","City":"\u82cf\u5dde\u5e02","CompanyShortName":"\u5317\u4eac\u725b\u7535\u79d1\u6280\u6709\u9650\u8d23\u4efb\u516c\u53f8","IndustryField":"\u7535\u5b50\u5546\u52a1 \u00b7 \u786c\u4ef6","Upper class of industry":"IT\u6280\u672f,\u7535\u5b50\u5236\u9020"},{"Provience":"\u6c5f\u82cf","City":"\u82cf\u5dde\u5e02","CompanyShortName":"\u82cf\u5dde\u8d85\u96c6\u4fe1\u606f\u79d1\u6280\u6709\u9650\u516c\u53f8","IndustryField":"\u6570\u636e\u670d\u52a1 \u00b7 \u786c\u4ef6","Upper class of industry":"IT\u6280\u672f,\u7535\u5b50\u5236\u9020"},{"Provience":"\u6c5f\u82cf","City":"\u82cf\u5dde\u5e02","CompanyShortName":"\u82cf\u5dde\u89e6\u8fbe\u4fe1\u606f\u6280\u672f\u6709\u9650\u516c\u53f8","IndustryField":"\u79fb\u52a8\u4e92\u8054\u7f51 \u00b7 \u786c\u4ef6","Upper class of industry":"IT\u6280\u672f,\u7535\u5b50\u5236\u9020"},{"Provience":"\u6c5f\u82cf","City":"\u82cf\u5dde\u5e02","CompanyShortName":"\u82cf\u5dde\u4e1c\u9f0e\u8363\u7535\u5b50\u79d1\u6280\u6709\u9650\u516c\u53f8","IndustryField":"\u7535\u5b50\u5546\u52a1 \u00b7 \u786c\u4ef6","Upper class of industry":"IT\u6280\u672f,\u7535\u5b50\u5236\u9020"},{"Provience":"\u6c5f\u82cf","City":"\u82cf\u5dde\u5e02","CompanyShortName":"\u798f\u5efa\u8054\u8fea\u5546\u7528\u8bbe\u5907\u6709\u9650\u516c\u53f8","IndustryField":"\u79fb\u52a8\u4e92\u8054\u7f51 \u00b7 \u786c\u4ef6","Upper class of industry":"IT\u6280\u672f,\u7535\u5b50\u5236\u9020"},{"Provience":"\u6c5f\u82cf","City":"\u82cf\u5dde\u5e02","CompanyShortName":"\u4e0a\u6d77\u535a\u8f95\u4fe1\u606f\u6280\u672f\u670d\u52a1\u6709\u9650\u516c\u53f8","IndustryField":"\u786c\u4ef6 \u00b7 \u6570\u636e\u670d\u52a1","Upper class of industry":"IT\u6280\u672f,\u7535\u5b50\u5236\u9020"},{"Provience":"\u6c5f\u82cf","City":"\u82cf\u5dde\u5e02","CompanyShortName":"\u82cf\u5dde\u58f9\u70b9\u7ea2\u8f6f\u4ef6\u79d1\u6280\u6709\u9650\u516c\u53f8","IndustryField":"\u79fb\u52a8\u4e92\u8054\u7f51 \u00b7 \u786c\u4ef6","Upper class of industry":"IT\u6280\u672f,\u7535\u5b50\u5236\u9020"}]