[{"Provience":"\u5e7f\u4e1c","City":"\u73e0\u6d77\u5e02","CompanyShortName":"\u73e0\u6d77\u5341\u65b9\u9f0e\u798f\u79d1\u6280\u6709\u9650\u516c\u53f8","IndustryField":"\u79fb\u52a8\u4e92\u8054\u7f51 \u00b7 \u5e7f\u544a\u8425\u9500","Upper class of industry":"IT\u6280\u672f,\u91d1\u878d\u8d22\u7ecf"},{"Provience":"\u5e7f\u4e1c","City":"\u73e0\u6d77\u5e02","CompanyShortName":"\u534e\u6da6\u94f6\u884c\u80a1\u4efd\u6709\u9650\u516c\u53f8","IndustryField":"\u79fb\u52a8\u4e92\u8054\u7f51 \u00b7 \u91d1\u878d","Upper class of industry":"IT\u6280\u672f,\u91d1\u878d\u8d22\u7ecf"},{"Provience":"\u5e7f\u4e1c","City":"\u73e0\u6d77\u5e02","CompanyShortName":"\u4e0a\u6d77\u65b9\u4ed8\u901a\u5546\u52a1\u670d\u52a1\u6709\u9650\u516c\u53f8","IndustryField":"\u79fb\u52a8\u4e92\u8054\u7f51 \u00b7 \u91d1\u878d","Upper class of industry":"IT\u6280\u672f,\u91d1\u878d\u8d22\u7ecf"},{"Provience":"\u5e7f\u4e1c","City":"\u73e0\u6d77\u5e02","CompanyShortName":"\u6df1\u5733\u5e02\u666e\u667a\u6b63\u5143\u79d1\u6280\u4f20\u5a92\u6709\u9650\u516c\u53f8","IndustryField":"\u79fb\u52a8\u4e92\u8054\u7f51 \u00b7 \u5e7f\u544a\u8425\u9500","Upper class of industry":"IT\u6280\u672f,\u91d1\u878d\u8d22\u7ecf"},{"Provience":"\u5e7f\u4e1c","City":"\u73e0\u6d77\u5e02","CompanyShortName":"\u4e2d\u539f\u6a2a\u7434\u5730\u4ea7\u4ee3\u7406\u6709\u9650\u516c\u53f8","IndustryField":"\u91d1\u878d \u00b7 \u79fb\u52a8\u4e92\u8054\u7f51","Upper class of industry":"IT\u6280\u672f,\u91d1\u878d\u8d22\u7ecf"},{"Provience":"\u5e7f\u4e1c","City":"\u73e0\u6d77\u5e02","CompanyShortName":"\u73e0\u6d77\u5ba3\u4f20\u6613\u7f51\u7edc\u79d1\u6280\u6709\u9650\u516c\u53f8","IndustryField":"\u79fb\u52a8\u4e92\u8054\u7f51 \u00b7 \u5e7f\u544a\u8425\u9500","Upper class of industry":"IT\u6280\u672f,\u91d1\u878d\u8d22\u7ecf"},{"Provience":"\u5e7f\u4e1c","City":"\u73e0\u6d77\u5e02","CompanyShortName":"\u597d\u4e70\u8d22\u5bcc\u7ba1\u7406\u80a1\u4efd\u6709\u9650\u516c\u53f8","IndustryField":"\u7535\u5b50\u5546\u52a1 \u00b7 \u91d1\u878d","Upper class of industry":"IT\u6280\u672f,\u91d1\u878d\u8d22\u7ecf"},{"Provience":"\u5e7f\u4e1c","City":"\u73e0\u6d77\u5e02","CompanyShortName":"\u7eac\u6cd3\u8f6f\u4ef6\uff08\u73e0\u6d77\uff09\u6709\u9650\u516c\u53f8","IndustryField":"\u4f01\u4e1a\u670d\u52a1 \u00b7 \u91d1\u878d","Upper class of industry":"IT\u6280\u672f,\u91d1\u878d\u8d22\u7ecf"},{"Provience":"\u5e7f\u4e1c","City":"\u73e0\u6d77\u5e02","CompanyShortName":"\u5e7f\u5dde\u6d77\u8c5a\u4fe1\u606f\u79d1\u6280\u6709\u9650\u516c\u53f8","IndustryField":"O2O \u00b7 \u91d1\u878d","Upper class of industry":"IT\u6280\u672f,\u91d1\u878d\u8d22\u7ecf"}]