[{"Provience":"\u6cb3\u5357","City":"\u5b89\u9633\u5e02","CompanyShortName":"\u6df1\u5733\u5e02\u767e\u5229\u8d22\u5bcc\u4fe1\u606f\u54a8\u8be2\u6709\u9650\u516c\u53f8","IndustryField":"\u7535\u5b50\u5546\u52a1 \u00b7 \u91d1\u878d","Upper class of industry":"IT\u6280\u672f,\u91d1\u878d\u8d22\u7ecf"},{"Provience":"\u6cb3\u5357","City":"\u5b89\u9633\u5e02","CompanyShortName":"\u6cb3\u5357\u4e07\u5e84\u519c\u8d44\u7535\u5b50\u5546\u52a1\u6709\u9650\u516c\u53f8","IndustryField":"\u7535\u5b50\u5546\u52a1 \u00b7 \u5176\u4ed6","Upper class of industry":"IT\u6280\u672f"},{"Provience":"\u6cb3\u5357","City":"\u5b89\u9633\u5e02","CompanyShortName":"\u5317\u4eac\u9ea6\u8c46\u975e\u51e1\u79d1\u6280\u6709\u9650\u516c\u53f8","IndustryField":"\u79fb\u52a8\u4e92\u8054\u7f51","Upper class of industry":"IT\u6280\u672f"},{"Provience":"\u6cb3\u5357","City":"\u5b89\u9633\u5e02","CompanyShortName":"\u6df1\u5733\u5e02\u58f9\u634c\u65e0\u7ebf\u79d1\u6280\u6709\u9650\u516c\u53f8","IndustryField":"\u79fb\u52a8\u4e92\u8054\u7f51","Upper class of industry":"IT\u6280\u672f"},{"Provience":"\u6cb3\u5357","City":"\u5b89\u9633\u5e02","CompanyShortName":"\u5317\u4eac\u7075\u96e8\u4fe1\u606f\u6280\u672f\u6709\u9650\u516c\u53f8","IndustryField":"\u79fb\u52a8\u4e92\u8054\u7f51","Upper class of industry":"IT\u6280\u672f"}]