[{"newSalary":"0K-3K","name":"1-3\u5e74","value":124},{"newSalary":"0K-3K","name":"1\u5e74\u4ee5\u4e0b","value":48},{"newSalary":"0K-3K","name":"3-5\u5e74","value":3},{"newSalary":"0K-3K","name":"\u4e0d\u9650","value":178},{"newSalary":"0K-3K","name":"\u5e94\u5c4a\u6bd5\u4e1a\u751f","value":40},{"newSalary":"10K-15K","name":"1-3\u5e74","value":106},{"newSalary":"10K-15K","name":"10\u5e74\u4ee5\u4e0a","value":2},{"newSalary":"10K-15K","name":"3-5\u5e74","value":203},{"newSalary":"10K-15K","name":"5-10\u5e74","value":80},{"newSalary":"10K-15K","name":"\u4e0d\u9650","value":36},{"newSalary":"15K-25K","name":"1-3\u5e74","value":5},{"newSalary":"15K-25K","name":"10\u5e74\u4ee5\u4e0a","value":1},{"newSalary":"15K-25K","name":"3-5\u5e74","value":28},{"newSalary":"15K-25K","name":"5-10\u5e74","value":30},{"newSalary":"15K-25K","name":"\u4e0d\u9650","value":2},{"newSalary":"25K-50K","name":"10\u5e74\u4ee5\u4e0a","value":2},{"newSalary":"25K-50K","name":"3-5\u5e74","value":2},{"newSalary":"25K-50K","name":"5-10\u5e74","value":8},{"newSalary":"25K-50K","name":"\u4e0d\u9650","value":8},{"newSalary":"3K-5K","name":"1-3\u5e74","value":829},{"newSalary":"3K-5K","name":"1\u5e74\u4ee5\u4e0b","value":36},{"newSalary":"3K-5K","name":"3-5\u5e74","value":103},{"newSalary":"3K-5K","name":"5-10\u5e74","value":1},{"newSalary":"3K-5K","name":"\u4e0d\u9650","value":270},{"newSalary":"3K-5K","name":"\u5e94\u5c4a\u6bd5\u4e1a\u751f","value":42},{"newSalary":"5K-7K","name":"1-3\u5e74","value":660},{"newSalary":"5K-7K","name":"10\u5e74\u4ee5\u4e0a","value":1},{"newSalary":"5K-7K","name":"1\u5e74\u4ee5\u4e0b","value":17},{"newSalary":"5K-7K","name":"3-5\u5e74","value":247},{"newSalary":"5K-7K","name":"5-10\u5e74","value":14},{"newSalary":"5K-7K","name":"\u4e0d\u9650","value":204},{"newSalary":"5K-7K","name":"\u5e94\u5c4a\u6bd5\u4e1a\u751f","value":21},{"newSalary":"7K-10K","name":"1-3\u5e74","value":482},{"newSalary":"7K-10K","name":"1\u5e74\u4ee5\u4e0b","value":13},{"newSalary":"7K-10K","name":"3-5\u5e74","value":348},{"newSalary":"7K-10K","name":"5-10\u5e74","value":48},{"newSalary":"7K-10K","name":"\u4e0d\u9650","value":94},{"newSalary":"7K-10K","name":"\u5e94\u5c4a\u6bd5\u4e1a\u751f","value":8}]