[{"word": "销售", "value": 8}, {"word": "课程", "value": 2}, {"word": "售前", "value": 2}, {"word": "咨询", "value": 2}, {"word": "网站", "value": 2}, {"word": "编辑", "value": 2}, {"word": "运营", "value": 2}, {"word": "前台", "value": 2}, {"word": "平面设计", "value": 1}, {"word": "兼办", "value": 1}, {"word": "办公", "value": 1}, {"word": "讲师", "value": 1}, {"word": "客服", "value": 1}, {"word": "手", "value": 1}, {"word": "游", "value": 1}, {"word": "游戏", "value": 1}, {"word": "游戏网", "value": 1}, {"word": "C++", "value": 1}, {"word": "商务", "value": 1}, {"word": "PHP", "value": 1}, {"word": "架构", "value": 1}, {"word": "架构师", "value": 1}, {"word": "前端", "value": 1}, {"word": "研发", "value": 1}, {"word": "产品", "value": 1}, {"word": "美工", "value": 1}, {"word": "工技", "value": 1}, {"word": "技术", "value": 1}, {"word": "监销", "value": 1}, {"word": "项目", "value": 1}, {"word": "申报", "value": 1}, {"word": "报经", "value": 1}, {"word": "经理人", "value": 1}, {"word": "人力", "value": 1}, {"word": "人力资源", "value": 1}, {"word": "马鞍", "value": 1}, {"word": "马鞍山", "value": 1}, {"word": "鞍山", "value": 1}, {"word": "出纳", "value": 1}, {"word": "总裁", "value": 1}, {"word": "教育", "value": 1}, {"word": "行业", "value": 1}, {"word": "咨询师", "value": 1}, {"word": "客户经理", "value": 1}]