[{"Provience":"\u6c5f\u82cf","City":"\u5357\u4eac\u5e02","CompanyShortName":"\u5357\u4eac\u8f6f\u6838\u79d1\u6280\u6709\u9650\u516c\u53f8","IndustryField":"\u5176\u4ed6","Upper class of industry":"\u5176\u4ed6"},{"Provience":"\u6c5f\u82cf","City":"\u5357\u4eac\u5e02","CompanyShortName":"\u6c5f\u82cf\u5357\u5927\u4e94\u7ef4\u7535\u5b50\u79d1\u6280\u6709\u9650\u516c\u53f8","IndustryField":"\u5176\u4ed6","Upper class of industry":"\u5176\u4ed6"},{"Provience":"\u6c5f\u82cf","City":"\u5357\u4eac\u5e02","CompanyShortName":"\u5357\u4eac\u5927\u7ffc\u822a\u7a7a\u79d1\u6280\u6709\u9650\u516c\u53f8","IndustryField":"\u5176\u4ed6","Upper class of industry":"\u5176\u4ed6"},{"Provience":"\u6c5f\u82cf","City":"\u5357\u4eac\u5e02","CompanyShortName":"\u5357\u4eac\u534e\u8bbe\u79d1\u6280\u80a1\u4efd\u6709\u9650\u516c\u53f8","IndustryField":"\u5176\u4ed6","Upper class of industry":"\u5176\u4ed6"},{"Provience":"\u6c5f\u82cf","City":"\u5357\u4eac\u5e02","CompanyShortName":"\u5357\u4eac\u4e2d\u79d1\u6c34\u6cbb\u7406\u80a1\u4efd\u6709\u9650\u516c\u53f8","IndustryField":"\u5176\u4ed6","Upper class of industry":"\u5176\u4ed6"},{"Provience":"\u6c5f\u82cf","City":"\u5357\u4eac\u5e02","CompanyShortName":"\u5e7f\u5dde\u5929\u6a59\u5e7f\u544a\u6709\u9650\u516c\u53f8","IndustryField":"\u5176\u4ed6","Upper class of industry":"\u5176\u4ed6"},{"Provience":"\u6c5f\u82cf","City":"\u5357\u4eac\u5e02","CompanyShortName":"\u5357\u4eac\u60e0\u5927\u8861\u901a\u8f6f\u4ef6\u6280\u672f\u6709\u9650\u516c\u53f8","IndustryField":"\u5176\u4ed6","Upper class of industry":"\u5176\u4ed6"},{"Provience":"\u6c5f\u82cf","City":"\u5357\u4eac\u5e02","CompanyShortName":"\u5357\u4eac\u5609\u6052\u4fe1\u606f\u6280\u672f\u6709\u9650\u516c\u53f8","IndustryField":"\u5176\u4ed6","Upper class of industry":"\u5176\u4ed6"},{"Provience":"\u6c5f\u82cf","City":"\u5357\u4eac\u5e02","CompanyShortName":"\u6c5f\u82cf\u5eb7\u4f17\u5b9e\u4e1a\u6295\u8d44\u6709\u9650\u516c\u53f8","IndustryField":"\u5176\u4ed6","Upper class of industry":"\u5176\u4ed6"},{"Provience":"\u6c5f\u82cf","City":"\u5357\u4eac\u5e02","CompanyShortName":"\u5357\u4eac\u7231\u5fc5\u68a6\u751f\u7269\u6750\u6599\u6709\u9650\u516c\u53f8","IndustryField":"\u5176\u4ed6","Upper class of industry":"\u5176\u4ed6"},{"Provience":"\u6c5f\u82cf","City":"\u5357\u4eac\u5e02","CompanyShortName":"\u5357\u4eac\u666f\u66dc\u667a\u80fd\u79d1\u6280\u6709\u9650\u516c\u53f8","IndustryField":"\u5176\u4ed6","Upper class of industry":"\u5176\u4ed6"},{"Provience":"\u6c5f\u82cf","City":"\u5357\u4eac\u5e02","CompanyShortName":"\u6c5f\u82cf\u7d2b\u7c73\u7535\u5b50\u6280\u672f\u6709\u9650\u516c\u53f8","IndustryField":"\u5176\u4ed6","Upper class of industry":"\u5176\u4ed6"},{"Provience":"\u6c5f\u82cf","City":"\u5357\u4eac\u5e02","CompanyShortName":"\u53a6\u95e8\u677e\u9716\u79d1\u6280\u6709\u9650\u516c\u53f8","IndustryField":"\u5176\u4ed6","Upper class of industry":"\u5176\u4ed6"},{"Provience":"\u6c5f\u82cf","City":"\u5357\u4eac\u5e02","CompanyShortName":"\u5357\u4eac\u878d\u6cf0\u4fe1\u606f\u6280\u672f\u6709\u9650\u516c\u53f8","IndustryField":"\u5176\u4ed6","Upper class of industry":"\u5176\u4ed6"},{"Provience":"\u6c5f\u82cf","City":"\u5357\u4eac\u5e02","CompanyShortName":"\u5357\u4eac\u6069\u6676\u751f\u7269\u79d1\u6280\u6709\u9650\u516c\u53f8","IndustryField":"\u5176\u4ed6","Upper class of industry":"\u5176\u4ed6"},{"Provience":"\u6c5f\u82cf","City":"\u5357\u4eac\u5e02","CompanyShortName":"\u5357\u4eac\u7f8e\u8fb0\u5fae\u7535\u5b50\u6709\u9650\u516c\u53f8","IndustryField":"\u5176\u4ed6","Upper class of industry":"\u5176\u4ed6"},{"Provience":"\u6c5f\u82cf","City":"\u5357\u4eac\u5e02","CompanyShortName":"\u5357\u4eac\u591a\u4f26\u79d1\u6280\u80a1\u4efd\u6709\u9650\u516c\u53f8","IndustryField":"\u5176\u4ed6","Upper class of industry":"\u5176\u4ed6"},{"Provience":"\u6c5f\u82cf","City":"\u5357\u4eac\u5e02","CompanyShortName":"\u5317\u4eac\u534e\u65ed\u5de5\u7a0b\u9879\u76ee\u7ba1\u7406\u6709\u9650\u516c\u53f8","IndustryField":"\u5176\u4ed6","Upper class of industry":"\u5176\u4ed6"},{"Provience":"\u6c5f\u82cf","City":"\u5357\u4eac\u5e02","CompanyShortName":"\u5357\u4eac\u6377\u654f\u4fe1\u8f6f\u4ef6\u79d1\u6280\u6709\u9650\u516c\u53f8","IndustryField":"\u5176\u4ed6","Upper class of industry":"\u5176\u4ed6"}]